Workbook
Name Amt: "Text Box 56"
Name Beg_Bal: #REF!
Name cat: #REF!
Name cost: #REF!
Name Data: #REF!
Name eee: #REF!
Name End_Bal: #REF!
Name Excel_BuiltIn__FilterDatabase_1: #REF!
Name Excel_BuiltIn_Print_Area_1_1: #REF!
Name Excel_BuiltIn_Print_Titles_1_1: #REF!
Name Extra_Pay: #REF!
Name ffff: [14]รายละเอียดสถานี!#REF!
Name Full_Print: #REF!
Name fwedqw: #REF!
Name Header_Row: ROW(#REF!)
Name Int: #REF!
Name Interest_Rate: #REF!
Name Last_Row: #N/A
Name Loan_Amount: #REF!
Name Loan_Start: #REF!
Name Loan_Years: #REF!
Name Num_Pmt_Per_Year: #REF!
Name Number_of_Payments: MATCH(0.01,End_Bal,-1)+1
Name p: #REF!
Name Pay_Date: #REF!
Name Pay_Num: #REF!
Name Payment_Date: DATE(YEAR(Loan_Start),MONTH(Loan_Start)+Payment_Number,DAY(Loan_Start))
Name Princ: #REF!
Name Print_Area_Reset: OFFSET(Full_Print,0,0,Last_Row)
Name Productos2: #REF!
Name Sched_Pay: #REF!
Name Scheduled_Extra_Payments: #REF!
Name Scheduled_Interest_Rate: #REF!
Name Scheduled_Monthly_Payment: #REF!
Name sdwsdsd: DATE(YEAR([0]!Loan_Start),MONTH([0]!Loan_Start)+Payment_Number,DAY([0]!Loan_Start))
Name sgd: #REF!
Name spare: #REF!
Name ssss: #REF!
Name Subcat: [14]รายละเอียดสถานี!#REF!
Name Total_Interest: #REF!
Name Total_Pay: #REF!
Name Total_Payment: Scheduled_Payment+Extra_Payment
Name uighghi: DATE(YEAR([0]!Loan_Start),MONTH([0]!Loan_Start)+Payment_Number,DAY([0]!Loan_Start))
Name Values_Entered: IF(Loan_Amount*Interest_Rate*Loan_Years*Loan_Start>0,1,0)
Name wdqddfwefq: #REF!
Name wewe: DATE(YEAR([0]!Loan_Start),MONTH([0]!Loan_Start)+Payment_Number,DAY([0]!Loan_Start))
Name ww: DATE(YEAR([0]!Loan_Start),MONTH([0]!Loan_Start)+Payment_Number,DAY([0]!Loan_Start))
Name www: DATE(YEAR([0]!Loan_Start),MONTH([0]!Loan_Start)+Payment_Number,DAY([0]!Loan_Start))
Name zxCCC: #REF!
Name ฤฆฤห: #REF!
Name cost: #REF!
Name Data: #REF!
Name eee: #REF!
Name ffff: [14]รายละเอียดสถานี!#REF!
Name Number_of_Payments: MATCH(0.01,[0]!End_Bal,-1)+1
Name p: #REF!
Name Payment_Date: DATE(YEAR([0]!Loan_Start),MONTH([0]!Loan_Start)+Payment_Number,DAY([0]!Loan_Start))
Name Print_Area_Reset: OFFSET([0]!Full_Print,0,0,[0]!Last_Row)
Name sdwsdsd: DATE(YEAR([19]!Loan_Start),MONTH([19]!Loan_Start)+Payment_Number,DAY([19]!Loan_Start))
Name Subcat: [14]รายละเอียดสถานี!#REF!

Sheet Summary Cost
A2: Tender No : | C2: MA2025-XXX
A3: Project Name : | C3: การจ้างบำรุงรักษา...
A4: Project Value (Include Vat 7%) : | C4: 22500000 | D4: 1 | E4: =BAHTTEXT(C4)
A5: Project Value (Exclude Vat 7%) : | C5: =C4*100/107 | D5: =SUM(D6:D7) | E5: =BAHTTEXT(C5)
A6: Summary Cost 1-4 : | C6: =SUM(I10,I15,I20,I31) | D6: =C6/$C$5 | E6: =BAHTTEXT(C6)
A7: Gross Profit : | C7: =C5-C6 | D7: =C7/$C$5 | E7: =BAHTTEXT(C7)
A9: ลำดับ | B9: รายละเอียด | C9: Cost Code | D9: ระยะเวลา | E9: หน่วย | F9: จำนวน | G9: หน่วย | H9: ราคา/หน่วย | I9: ราคารวม | J9: หมายเหตุ
A10: 1 | B10: จัดซื้อวัสดุและอุปกรณ์ | H10: SUM 1 | I10: =SUM(I11:I14)
A11: 1.1 | B11: อุปกรณ์-ซื้อภายในประเทศ | C11: C002011
A12: P | B12: จัดซื้อ Tools และวัสดุสิ้นเปลือง | D12: 1 | E12: Time | F12: 1 | G12: Time | I12: ='เครื่องมือช่าง (Tools)'!D12 | J12: เครื่องมือช่าง (Tools)'!A1
A13: P | B13: จัดซื้อวัสดุสิ้นเปลือง | D13: 1 | E13: Time | F13: 1 | G13: Time | I13: ='อะไหล่และวัสดุสิ้นเปลือง'!D8 | J13: อะไหล่และวัสดุสิ้นเปลือง!A1
A14: F | B14: เงินสำรองในการซื้อ Spare Part เพิ่มเติม | D14: 12 | E14: เดือน | F14: 0.01 | G14: โครงการ | I14: =C5*F14
A15: 2 | B15: จัดจ้าง | H15: SUM 2 | I15: =SUM(I17:I19)
A16: 2.1 | B16: ค่าจ้างเหมา Sub Contractor | C16: C003011
A17: F | B17: เงินสำรองในการจัดจ้าง Sub Contractor | D17: 12 | E17: เดือน | F17: 0.01 | G17: โครงการ | I17: =C5*F17
A18: F | B18: เงินสำรองซ่อมแซมอุปกรณ์หมุนเวียนงานซ่อม | D18: 12 | E18: เดือน | F18: 0.01 | G18: โครงการ | I18: =C5*F18
A19: F | B19: ค่าใช้จ่ายในการจ้าง Subcontractor | D19: 1 | E19: Time | F19: 1 | G19: Time | I19: =Outsource!I3 | J19: Outsource!I3
A20: 3 | B20: Project OPEX | H20: SUM 3 | I20: =SUM(I21:I30)
A21: 3.1 | B21: ค่าสาธารณูปโภค (เช่น น้ำ,ไฟ,โทรศัพท์,อินเตอร์เน็ต) | C21: G010321
A22: F | B22: ค่าบริการเลขหมายโทรศัพท์ที่ใช้ในโครงการ | D22: 12 | E22: เดือน | F22: 1 | G22: เดือน | H22: ='Telephone fee'!E8 | I22: =H22*F22*D22 | J22: Telephone fee'!A1
A23: 3.2 | B23: ค่าใช้จ่ายสำนักงาน | C23: G010311
A24: F | B24: Monthly Report Document | D24: 12 | E24: เดือน | F24: 1 | G24: เดือน | H24: 2000 | I24: =H24*F24*D24
A25: 3.3 | B25: ค่าเช่าทรัพย์สินและสถานที่ | C25: G010411
A26: F
A27: 3.4 | B27: คชจ.เดินทางสาธารณะและรถยนต์ | C27: G010231
A28: F | B28: ค่าใช้จ่ายในการเดินทาง | D28: 12 | E28: เดือน | F28: 1 | G28: เดือน | H28: 3000 | I28: =H28*D28*F28
A29: 3.5 | B29: คชจ.โครงการสำหรับการประชุม (ตรวจรับงาน)
A30: F | B30: ค่าใช้จ่ายในการประชุมและตรวจรับงาน | D30: 12 | E30: เดือน | F30: 1 | G30: โครงการ | H30: 15000 | I30: =H30*F30*D30
A31: 4 | B31: Manpower | C31: C003081 | H31: SUM 4 | I31: =SUM(I33:I40)
A32: 4.1 | B32: ค่าแรงพนักงาน AMR | C32: C003071
A33: F | B33: Management and Support Group | C33: 1 | D33: 3 | E33: เดือน | F33: 1 | G33: เดือน | H33: ='Manpower rate'!E4 | I33: =H33*F33*D33
A34: F | B34: Maintenance Project Leader | C34: 1 | D34: 12 | E34: เดือน | F34: 1 | G34: เดือน | H34: ='Manpower rate'!E5 | I34: =H34*F34*D34
A35: F | B35: Supervisor x2 | C35: 2 | D35: 12 | E35: เดือน | F35: 1 | G35: เดือน | H35: ='Manpower rate'!E6 | I35: =H35*F35*D35*C35
A36: F | B36: Engineer x5 | C36: 5 | D36: 12 | E36: เดือน | F36: 1 | G36: เดือน | H36: ='Manpower rate'!E7 | I36: =H36*F36*D36*C36
A37: F | B37: Technician x34 | C37: 34 | D37: 12 | E37: เดือน | F37: 1 | G37: เดือน | H37: ='Manpower rate'!E8 | I37: =H37*F37*D37*C37
A38: F | B38: Admin x1 | C38: 1 | D38: 12 | E38: เดือน | F38: 1 | G38: เดือน | H38: ='Manpower rate'!E9 | I38: =H38*F38*D38*C38
A39: 4.2 | B39: Extra Cost | C39: JV | H39: ='Manpower rate'!E10
A40: F | B40: On Call (Weekend) | E40: Days | F40: 1 | G40: Day | I40: =H40*F40*D40

Sheet เครื่องมือช่าง (Tools)
A1: รายการเครื่องมือช่าง (Tools)

Sheet อะไหล่และวัสดุสิ้นเปลือง
A1: รายการอะไหล่และวัสดุสิ้นเปลือง (Spare Parts)

Sheet Outsource
A1: Item | B1: Description | C1: Cost Code | D1: Duration | F1: Cost | J1: Remarl
D2: Quantity | E2: Unit | F2: Quantity | G2: Unit | H2: Cost/Unit | I2: Total
B3: Outsource | C3: C003011 | G3: SUM | I3: =SUM(I4:I6)

Sheet Telephone fee
A1: Telephone
A2: ลำดับ | B2: ตำแหน่ง | C2: จำนวน | D2: Telephone Cost | E2: ราคา
A4: 1 | B4: Maintenance Leader | C4: 1 | D4: 800 | E4: =C4*D4
A5: 2 | B5: Supervisor | C5: 2 | D5: 399 | E5: =C5*D5
A6: 3 | B6: Engineer | C6: 5 | D6: 399 | E6: =C6*D6
A7: 4 | B7: Technician | C7: 34 | D7: 299 | E7: =C7*D7
E8: =SUM(E4:E7)

Sheet Manpower rate
A1: Manpower rate
A2: ลำดับ | B2: ตำแหน่ง | C2: Salary rate/Month | D2: Other benefit | E2: Summary/Month | I2: Management group
I3: Deputy Operation & Maintenance Director
A4: 1 | B4: Management Group Cost | C4: 150000 | E4: =C4+D4 | I4: Maintenance Manager
A5: 2 | B5: Maintenance Project Leader | C5: 50000 | E5: =C5+D5 | I5: Section Chief – MA Office
A6: 3 | B6: Supervisor | C6: 30000 | E6: =C6+D6 | I6: MA Inventory Officer
A7: 4 | B7: Engineer | C7: 22000 | D7: 2000 | E7: =C7+D7 | I7: MA Inventory Officer
A8: 5 | B8: Technician | C8: 17000 | D8: 2000 | E8: =C8+D8 | I8: MA Coordinator
A9: 6 | B9: Admin | C9: 15000 | E9: =C9+D9

Sheet Action
A1: System | B1: Equipment | D1: Equipment Code | E1: Frequency | F1: Frequency Code | G1: PM Activity (AMR) | H1: Work time (hr.)

Sheet SUM
A1: สถานที่ (Location) | B1: ระบบ (System) | C1: อุปกรณ์ (ไทย) | D1: อุปกรณ์ (English) | E1: รหัสเก่า | F1: รหัส | G1: D1 | H1: W1 | I1: W4 / M1 | J1: M3 | K1: M6 | L1: Y1 | M1: จำนวน อุปกรณ์ | N1: คนทำงาน

Sheet PM Schedule plan
A1: Preventive Maintenance Schedule Plan
A2: Routine Location | B2: 1 | N2: 2 | Z2: 3 | AL2: 4 | AX2: 5 | BJ2: 6 | BV2: 7 | CH2: 8 | CT2: 9 | DF2: 10 | DR2: 11 | ED2: 12
B3: D1 | D3: W1 | F3: W4 / M1 | H3: M3 | J3: M6 | L3: Y1 | N3: D1 | P3: W1 | R3: W4 / M1 | T3: M3 | V3: M6 | X3: Y1 | Z3: D1 | AB3: W1 | AD3: W4 / M1 | AF3: M3 | AH3: M6 | AJ3: Y1 | AL3: D1 | AN3: W1 | AP3: W4 / M1 | AR3: M3 | AT3: M6 | AV3: Y1 | AX3: D1 | AZ3: W1 | BB3: W4 / M1 | BD3: M3 | BF3: M6 | BH3: Y1 | BJ3: D1 | BL3: W1 | BN3: W4 / M1 | BP3: M3 | BR3: M6 | BT3: Y1 | BV3: D1 | BX3: W1 | BZ3: W4 / M1 | CB3: M3 | CD3: M6 | CF3: Y1 | CH3: D1 | CJ3: W1 | CL3: W4 / M1 | CN3: M3 | CP3: M6 | CR3: Y1 | CT3: D1 | CV3: W1 | CX3: W4 / M1 | CZ3: M3 | DB3: M6 | DD3: Y1 | DF3: D1 | DH3: W1 | DJ3: W4 / M1 | DL3: M3 | DN3: M6 | DP3: Y1 | DR3: D1 | DT3: W1 | DV3: W4 / M1 | DX3: M3 | DZ3: M6 | EB3: Y1 | ED3: D1 | EF3: W1 | EH3: W4 / M1 | EJ3: M3 | EL3: M6 | EN3: Y1
B4: SYS | C4: TT (hr) | D4: SYS | E4: TT (hr) | F4: SYS | G4: TT (hr) | H4: SYS | I4: TT (hr) | J4: SYS | K4: TT (hr) | L4: SYS | M4: TT (hr) | N4: SYS | O4: TT (hr) | P4: SYS | Q4: TT (hr) | R4: SYS | S4: TT (hr) | T4: SYS | U4: TT (hr) | V4: SYS | W4: TT (hr) | X4: SYS | Y4: TT (hr) | Z4: SYS | AA4: TT (hr) | AB4: SYS | AC4: TT (hr) | AD4: SYS | AE4: TT (hr) | AF4: SYS | AG4: TT (hr) | AH4: SYS | AI4: TT (hr) | AJ4: SYS | AK4: TT (hr) | AL4: SYS | AM4: TT (hr) | AN4: SYS | AO4: TT (hr) | AP4: SYS | AQ4: TT (hr) | AR4: SYS | AS4: TT (hr) | AT4: SYS | AU4: TT (hr) | AV4: SYS | AW4: TT (hr) | AX4: SYS | AY4: TT (hr) | AZ4: SYS | BA4: TT (hr) | BB4: SYS | BC4: TT (hr) | BD4: SYS | BE4: TT (hr) | BF4: SYS | BG4: TT (hr) | BH4: SYS | BI4: TT (hr) | BJ4: SYS | BK4: TT (hr) | BL4: SYS | BM4: TT (hr) | BN4: SYS | BO4: TT (hr) | BP4: SYS | BQ4: TT (hr) | BR4: SYS | BS4: TT (hr) | BT4: SYS | BU4: TT (hr) | BV4: SYS | BW4: TT (hr) | BX4: SYS | BY4: TT (hr) | BZ4: SYS | CA4: TT (hr) | CB4: SYS | CC4: TT (hr) | CD4: SYS | CE4: TT (hr) | CF4: SYS | CG4: TT (hr) | CH4: SYS | CI4: TT (hr) | CJ4: SYS | CK4: TT (hr) | CL4: SYS | CM4: TT (hr) | CN4: SYS | CO4: TT (hr) | CP4: SYS | CQ4: TT (hr) | CR4: SYS | CS4: TT (hr) | CT4: SYS | CU4: TT (hr) | CV4: SYS | CW4: TT (hr) | CX4: SYS | CY4: TT (hr) | CZ4: SYS | DA4: TT (hr) | DB4: SYS | DC4: TT (hr) | DD4: SYS | DE4: TT (hr) | DF4: SYS | DG4: TT (hr) | DH4: SYS | DI4: TT (hr) | DJ4: SYS | DK4: TT (hr) | DL4: SYS | DM4: TT (hr) | DN4: SYS | DO4: TT (hr) | DP4: SYS | DQ4: TT (hr) | DR4: SYS | DS4: TT (hr) | DT4: SYS | DU4: TT (hr) | DV4: SYS | DW4: TT (hr) | DX4: SYS | DY4: TT (hr) | DZ4: SYS | EA4: TT (hr) | EB4: SYS | EC4: TT (hr) | ED4: SYS | EE4: TT (hr) | EF4: SYS | EG4: TT (hr) | EH4: SYS | EI4: TT (hr) | EJ4: SYS | EK4: TT (hr) | EL4: SYS | EM4: TT (hr) | EN4: SYS | EO4: TT (hr)

Sheet PM Plan
A1: วงรอบการบำรุงรักษาเชิงป้องกัน
A2: Item | B2: System | C2: Sub-System | D2: Daily | E2: Weekly(W1) | F2: Monthly(M1) | G2: Three Month (M3) | H2: Six Month (M6) | I2: Yearly (Y1)

Sheet Abbreviation
A1: System | B1: ระบบ / อุปกรณ์ | C1: Sub-system/ Equipment | D1: Abbreviation

Sheet Roster design
A1: Item | B1: Full Name | D1: Roster
D2: 1 | E2: 2 | F2: 3 | G2: 4 | H2: 5 | I2: 6 | J2: 7 | K2: 8 | L2: 9 | M2: 10 | N2: 11 | O2: 12 | P2: 13 | Q2: 14 | R2: 15 | S2: 16 | T2: 17 | U2: 18 | V2: 19 | W2: 20 | X2: 21 | Y2: 22 | Z2: 23 | AA2: 24 | AB2: 25 | AC2: 26 | AD2: 27 | AE2: 28 | AF2: 29 | AG2: 30
D3: S | E3: S | F3: M | G3: T | H3: W | I3: T | J3: F | K3: S | L3: S | M3: M | N3: T | O3: W | P3: T | Q3: F | R3: S | S3: S | T3: M | U3: T | V3: W | W3: T | X3: F | Y3: S | Z3: S | AA3: M | AB3: T | AC3: W | AD3: T | AE3: F | AF3: S | AG3: S
